{
    "job_hash": "9264db2b833865c4a7a64a6f22c4bdb083a2cd045b7d00a04d1801a9c77b6661",
    "completed_parts": [
        0,
        1,
        2,
        3,
        4,
        5,
        6,
        7,
        8,
        9,
        10,
        11,
        12,
        13,
        14,
        15,
        16,
        17,
        18,
        19,
        20,
        21,
        22,
        23,
        24,
        25,
        26,
        27,
        28,
        29,
        30,
        31,
        32,
        33,
        34,
        35,
        36,
        37,
        38,
        39,
        40,
        41,
        42,
        43,
        44,
        45,
        46,
        47,
        48,
        49,
        50,
        51,
        52,
        53,
        54,
        55,
        56,
        57,
        58,
        59,
        60,
        61,
        62,
        63,
        64,
        65,
        66,
        67,
        68,
        69,
        70,
        71,
        72,
        73,
        74,
        75,
        76,
        77,
        78,
        79,
        80,
        81,
        82,
        83,
        84,
        85,
        86,
        87,
        88,
        89,
        90,
        91
    ],
    "best_result_so_far": {
        "best_chi2_dof": 5048792.419858156,
        "best_params": {
            "pl_norm": 0.001,
            "photon_index": 2.8,
            "nH": 1.0,
            "refl_norm": 0.1,
            "line_energy": 6.3428571428571425,
            "line_sigma": 0.3,
            "line_norm": 0.1
        },
        "best_result": {
            "chi_squared": 7118797312.0,
            "dof": 1410.0,
            "reduced_chi_squared": 5048792.419858156,
            "n_data_points": 1417
        }
    },
    "last_updated": "2025-12-18 20:50:07.652626"
}